{
  "applications": "*",
  "changelogDate": "20250422195856",
  "dto": "mapstruct",
  "entityTableName": "user_profile",
  "fields": [
    {
      "fieldName": "userId",
      "fieldType": "String",
      "fieldValidateRules": ["required", "unique"]
    },
    {
      "fieldName": "firstName",
      "fieldType": "String"
    },
    {
      "fieldName": "lastName",
      "fieldType": "String"
    },
    {
      "fieldName": "email",
      "fieldType": "String"
    },
    {
      "fieldName": "phone",
      "fieldType": "String"
    },
    {
      "fieldName": "addressLine1",
      "fieldType": "String"
    },
    {
      "fieldName": "addressLine2",
      "fieldType": "String"
    },
    {
      "fieldName": "city",
      "fieldType": "String"
    },
    {
      "fieldName": "state",
      "fieldType": "String"
    },
    {
      "fieldName": "zipCode",
      "fieldType": "String"
    },
    {
      "fieldName": "country",
      "fieldType": "String"
    },
    {
      "fieldName": "notes",
      "fieldType": "String"
    },
    {
      "fieldName": "createdAt",
      "fieldType": "ZonedDateTime",
      "fieldValidateRules": ["required"]
    },
    {
      "fieldName": "updatedAt",
      "fieldType": "ZonedDateTime",
      "fieldValidateRules": ["required"]
    }
  ],
  "jpaMetamodelFiltering": true,
  "name": "UserProfile",
  "pagination": "pagination",
  "relationships": [
    {
      "otherEntityName": "userSubscription",
      "otherEntityRelationshipName": "userProfile",
      "relationshipName": "userSubscription",
      "relationshipSide": "right",
      "relationshipType": "one-to-one"
    }
  ],
  "searchEngine": "no",
  "service": "serviceImpl"
}
